hasapi/__init__.py
hasapi/app.py
hasapi/cli.py
hasapi/docs.py
hasapi/exceptions.py
hasapi/openapi.py
hasapi/request.py
hasapi/response.py
hasapi/router.py
hasapi/utils.py
hasapi/websocket.py
hasapi/ai/__init__.py
hasapi/ai/chat_memory.py
hasapi/ai/embeddings.py
hasapi/ai/llm.py
hasapi/ai/rag.py
hasapi/ai/vectors/__init__.py
hasapi/ai/vectors/base.py
hasapi/ai/vectors/memory.py
hasapi/core/__init__.py
hasapi/core/engine.py
hasapi/core/request.py
hasapi/core/response.py
hasapi/core/router.py
hasapi/middleware/__init__.py
hasapi/middleware/auth.py
hasapi/middleware/base.py
hasapi/middleware/cors.py
hasapi/templates/__init__.py
hasapi/templates/engine.py
hasapi/templates/layout.py
hasapi/templates/response.py
hasapi/transport/__init__.py
hasapi/transport/base.py
hasapi/transport/python_engine.py
hasapi/ui/__init__.py
hasapi/ui/components.py
hasapi/ui/core.py
hasapi-0.1.1.dist-info/licenses/LICENSE
hasapi-0.1.1.dist-info/METADATA
hasapi-0.1.1.dist-info/WHEEL
hasapi-0.1.1.dist-info/entry_points.txt
hasapi-0.1.1.dist-info/top_level.txt
hasapi-0.1.1.dist-info/RECORD
