Metadata-Version: 2.4
Name: hasapi
Version: 0.1.1
Summary: Modern Python web framework for AI-native APIs (LLM + RAG + Streaming)
Author-email: HasAPI Team <team@hasapi.dev>
License-Expression: MIT
Project-URL: Homepage, https://github.com/Haslab-dev/HasAPI
Project-URL: Documentation, https://github.com/Haslab-dev/HasAPI#readme
Project-URL: Repository, https://github.com/Haslab-dev/HasAPI
Project-URL: Issues, https://github.com/Haslab-dev/HasAPI/issues
Keywords: ai,api,fastapi,rag,llm,vector db,asgi,websocket
Classifier: Programming Language :: Python :: 3
Classifier: Framework :: AsyncIO
Classifier: Intended Audience :: Developers
Classifier: Operating System :: OS Independent
Requires-Python: >=3.10
License-File: LICENSE
Requires-Dist: httpx>=0.24
Requires-Dist: orjson>=3.8
Requires-Dist: uvicorn[standard]>=0.20
Requires-Dist: uvloop>=0.19; sys_platform != "win32"
Requires-Dist: httptools>=0.6
Requires-Dist: pydantic>=2.0
Requires-Dist: typing-extensions>=4.5
Requires-Dist: python-dotenv>=1.0
Requires-Dist: websockets>=11.0
Requires-Dist: PyJWT>=2.8.0
Provides-Extra: ai
Requires-Dist: openai>=1.0; extra == "ai"
Requires-Dist: anthropic>=0.5; extra == "ai"
Provides-Extra: pytorch
Requires-Dist: torch>=2.0; extra == "pytorch"
Provides-Extra: onnx
Requires-Dist: onnxruntime>=1.15; extra == "onnx"
Provides-Extra: gguf
Requires-Dist: llama-cpp-python>=0.2; extra == "gguf"
Provides-Extra: vector
Requires-Dist: faiss-cpu>=1.7; extra == "vector"
Requires-Dist: numpy>=1.24; extra == "vector"
Provides-Extra: benchmark
Requires-Dist: fastapi>=0.100; extra == "benchmark"
Provides-Extra: all
Requires-Dist: torch>=2.0; extra == "all"
Requires-Dist: onnxruntime>=1.15; extra == "all"
Requires-Dist: faiss-cpu>=1.7; extra == "all"
Requires-Dist: llama-cpp-python>=0.2; extra == "all"
Requires-Dist: openai>=1.0; extra == "all"
Requires-Dist: anthropic>=0.5; extra == "all"
Requires-Dist: numpy>=1.24; extra == "all"
Requires-Dist: fastapi>=0.100; extra == "all"
Dynamic: license-file
